[
  {
    "topology_type": "BarabasiAlbert",
    "num_nodes": 200,
    "num_edges": 594,
    "num_tests": 1000,
    "successful_deliveries": 958,
    "failed_deliveries": 42,
    "success_rate": 0.958,
    "total_hops": 7371,
    "avg_hops": 7.6941544885177455,
    "total_optimal_hops": 2770,
    "avg_optimal_hops": 2.8914405010438413,
    "stretch_ratio": 2.66101083032491,
    "gravity_hops": 2191,
    "pressure_hops": 2926,
    "tree_hops": 2254,
    "ttl_failures": 42,
    "no_path_failures": 0,
    "elapsed_ms": 43
  },
  {
    "topology_type": "WattsStrogatz",
    "num_nodes": 200,
    "num_edges": 600,
    "num_tests": 1000,
    "successful_deliveries": 1000,
    "failed_deliveries": 0,
    "success_rate": 1.0,
    "total_hops": 7101,
    "avg_hops": 7.101,
    "total_optimal_hops": 4303,
    "avg_optimal_hops": 4.303,
    "stretch_ratio": 1.6502440158029281,
    "gravity_hops": 5166,
    "pressure_hops": 1655,
    "tree_hops": 280,
    "ttl_failures": 0,
    "no_path_failures": 0,
    "elapsed_ms": 34
  },
  {
    "topology_type": "Grid",
    "num_nodes": 200,
    "num_edges": 371,
    "num_tests": 1000,
    "successful_deliveries": 925,
    "failed_deliveries": 75,
    "success_rate": 0.925,
    "total_hops": 12672,
    "avg_hops": 13.69945945945946,
    "total_optimal_hops": 8554,
    "avg_optimal_hops": 9.247567567567568,
    "stretch_ratio": 1.4814122048164602,
    "gravity_hops": 4518,
    "pressure_hops": 7772,
    "tree_hops": 382,
    "ttl_failures": 75,
    "no_path_failures": 0,
    "elapsed_ms": 30
  },
  {
    "topology_type": "Random",
    "num_nodes": 200,
    "num_edges": 931,
    "num_tests": 1000,
    "successful_deliveries": 966,
    "failed_deliveries": 34,
    "success_rate": 0.966,
    "total_hops": 6410,
    "avg_hops": 6.635610766045549,
    "total_optimal_hops": 2477,
    "avg_optimal_hops": 2.5641821946169774,
    "stretch_ratio": 2.587807832054905,
    "gravity_hops": 2480,
    "pressure_hops": 2286,
    "tree_hops": 1644,
    "ttl_failures": 34,
    "no_path_failures": 0,
    "elapsed_ms": 46
  },
  {
    "topology_type": "RealWorld",
    "num_nodes": 200,
    "num_edges": 539,
    "num_tests": 1000,
    "successful_deliveries": 981,
    "failed_deliveries": 19,
    "success_rate": 0.981,
    "total_hops": 12286,
    "avg_hops": 12.523955147808358,
    "total_optimal_hops": 5554,
    "avg_optimal_hops": 5.661569826707441,
    "stretch_ratio": 2.212099387828592,
    "gravity_hops": 4944,
    "pressure_hops": 3839,
    "tree_hops": 3503,
    "ttl_failures": 19,
    "no_path_failures": 0,
    "elapsed_ms": 36
  }
]